heygen_mcp/__init__.py
heygen_mcp/client.py
heygen_mcp/exceptions.py
heygen_mcp/server.py
heygen_mcp/models/__init__.py
heygen_mcp/models/asset.py
heygen_mcp/models/avatar.py
heygen_mcp/models/avatar_group.py
heygen_mcp/models/base.py
heygen_mcp/models/folder.py
heygen_mcp/models/template.py
heygen_mcp/models/user.py
heygen_mcp/models/video.py
heygen_mcp/models/voice.py
heygen_mcp_sbroenne-0.3.1.dist-info/METADATA
heygen_mcp_sbroenne-0.3.1.dist-info/WHEEL
heygen_mcp_sbroenne-0.3.1.dist-info/entry_points.txt
heygen_mcp_sbroenne-0.3.1.dist-info/top_level.txt
heygen_mcp_sbroenne-0.3.1.dist-info/RECORD
