Metadata-Version: 2.4
Name: heygen-mcp-sbroenne
Version: 0.3.1
Summary: HeyGen MCP Server for AI Video Creation (Community Fork)
Author: Stefan Brenner
Maintainer: Stefan Brenner
License: MIT
Project-URL: Homepage, https://github.com/sbroenne/heygen-mcp
Project-URL: Repository, https://github.com/sbroenne/heygen-mcp
Project-URL: Bug Tracker, https://github.com/sbroenne/heygen-mcp/issues
Keywords: heygen,mcp,claude,ai,video,avatar
Classifier: Development Status :: 4 - Beta
Classifier: Intended Audience :: Developers
Classifier: License :: OSI Approved :: MIT License
Classifier: Programming Language :: Python :: 3
Classifier: Programming Language :: Python :: 3.10
Classifier: Programming Language :: Python :: 3.11
Classifier: Programming Language :: Python :: 3.12
Classifier: Programming Language :: Python :: 3.13
Requires-Python: >=3.10
Requires-Dist: mcp[cli]>=1.6.0
Requires-Dist: pydantic>=2.0.0
Requires-Dist: httpx>=0.27.0
Requires-Dist: python-dotenv>=1.0.0
Requires-Dist: tenacity>=8.0.0
Provides-Extra: dev
Requires-Dist: pytest; extra == "dev"
Requires-Dist: pytest-asyncio; extra == "dev"
Requires-Dist: ruff; extra == "dev"
Requires-Dist: pyright; extra == "dev"
Requires-Dist: build; extra == "dev"
Requires-Dist: twine; extra == "dev"
Requires-Dist: pre-commit; extra == "dev"
